ALU.v
module ALU (
    input clk,
    input rst,
    input [3:0] ALUop,
    input [31:0] A,
    input [31:0] B,
    output reg [31:0] Result,
    output reg Zero,
    output reg Carry,
    output reg Overflow,
    output reg Negative
);

    reg [32:0] tmp_result;  // 1-bit extra for carry

    always @(posedge clk or posedge rst) begin
        if (rst) begin
            Result   <= 0;
            Zero     <= 0;
            Carry    <= 0;
            Overflow <= 0;
            Negative <= 0;
        end else begin
            case (ALUop)
                4'b0000: begin // ADD
                    tmp_result = {1'b0, A} + {1'b0, B};
                    Result     <= tmp_result[31:0];
                    Carry      <= tmp_result[32];
                    Overflow   <= (A[31] == B[31]) && (tmp_result[31] != A[31]);
                end
                4'b0001: begin // SUB
                    tmp_result = {1'b0, A} - {1'b0, B};
                    Result     <= tmp_result[31:0];
                    Carry      <= tmp_result[32];
                    Overflow   <= (A[31] != B[31]) && (tmp_result[31] != A[31]);
                end
                4'b0010: Result <= A & B;       // AND
                4'b0011: Result <= A | B;       // OR
                4'b0100: Result <= A ^ B;       // XOR
                4'b0101: Result <= ~(A | B);    // NOR
                4'b0110: Result <= ($signed(A) < $signed(B)) ? 32'd1 : 32'd0; // SLT
                4'b0111: Result <= A << B[4:0]; // SLL
                4'b1000: Result <= A >> B[4:0]; // SRL
                default: Result <= 32'd0;
            endcase

            Zero     <= (Result == 0);
            Negative <= Result[31];
        end
    end
endmodule

ALU_tb.sv
`timescale 1ns/1ps

module ALU_tb;

    // DUT Inputs
    logic clk, rst;
    logic [3:0] ALUop;
    logic [31:0] A, B;

    // DUT Outputs
    logic [31:0] Result;
    logic Zero, Carry, Overflow, Negative;

    // Instantiate DUT
    ALU dut (
        .clk(clk),
        .rst(rst),
        .ALUop(ALUop),
        .A(A),
        .B(B),
        .Result(Result),
        .Zero(Zero),
        .Carry(Carry),
        .Overflow(Overflow),
        .Negative(Negative)
    );

    // Clock generation
    always #5 clk = ~clk;

    // Test sequence
    initial begin
        $dumpfile("alu.vcd");
        $dumpvars(0, ALU_tb);
        $monitor("Time=%0t | A=%0d B=%0d ALUop=%b => Result=%0d | Z=%b C=%b V=%b N=%b", 
                 $time, A, B, ALUop, Result, Zero, Carry, Overflow, Negative);

        clk = 0;
        rst = 1;
        ALUop = 4'b0000;
        A = 0;
        B = 0;
        #10 rst = 0;

        // ADD: no overflow
        A = 32'd10; B = 32'd5; ALUop = 4'b0000; #10;

        // ADD: signed overflow
        A = 32'd2_000_000_000; B = 32'd1_500_000_000; ALUop = 4'b0000; #10;

        // SUB: signed overflow
        A = -32'd2_000_000_000; B = 32'd1_000_000_000; ALUop = 4'b0001; #10;

        // SUB: no overflow
        A = 32'd20; B = 32'd5; ALUop = 4'b0001; #10;

        // AND
        A = 32'hFF00FF00; B = 32'h00FF00FF; ALUop = 4'b0010; #10;

        // OR
        ALUop = 4'b0011; #10;

        // XOR
        ALUop = 4'b0100; #10;

        // NOR
        ALUop = 4'b0101; #10;

        // SLT: A < B
        A = -32'd5; B = 32'd1; ALUop = 4'b0110; #10;

        // SLT: A > B
        A = 32'd5; B = -32'd1; ALUop = 4'b0110; #10;

        // SLL: shift left
        A = 32'h00000001; B = 32'd4; ALUop = 4'b0111; #10;

        // SRL: shift right
        A = 32'h00000080; B = 32'd3; ALUop = 4'b1000; #10;

        $finish;
    end

endmodule

alu.vcd
$date
	Wed Jul 16 11:21:22 2025
$end
$version
	Icarus Verilog
$end
$timescale
	1ps
$end
$scope module ALU_tb $end
$var wire 1 ! Zero $end
$var wire 32 " Result [31:0] $end
$var wire 1 # Overflow $end
$var wire 1 $ Negative $end
$var wire 1 % Carry $end
$var reg 32 & A [31:0] $end
$var reg 4 ' ALUop [3:0] $end
$var reg 32 ( B [31:0] $end
$var reg 1 ) clk $end
$var reg 1 * rst $end
$scope module dut $end
$var wire 32 + A [31:0] $end
$var wire 4 , ALUop [3:0] $end
$var wire 32 - B [31:0] $end
$var wire 1 ) clk $end
$var wire 1 * rst $end
$var reg 1 % Carry $end
$var reg 1 $ Negative $end
$var reg 1 # Overflow $end
$var reg 32 . Result [31:0] $end
$var reg 1 ! Zero $end
$var reg 33 / tmp_result [32:0] $end
$upscope $end
$upscope $end
$enddefinitions $end
$comment Show the parameter values. $end
$dumpall
$end
#0
$dumpvars
bx /
b0 .
b0 -
b0 ,
b0 +
1*
0)
b0 (
b0 '
b0 &
0%
0$
0#
b0 "
0!
$end
#5000
1)
#10000
0)
b101 (
b101 -
b1010 &
b1010 +
0*
#15000
1!
b1111 "
b1111 .
b1111 /
1)
#20000
0)
b1011001011010000010111100000000 (
b1011001011010000010111100000000 -
b1110111001101011001010000000000 &
b1110111001101011001010000000000 +
#25000
0!
1#
b11010000100111011100001100000000 "
b11010000100111011100001100000000 .
b11010000100111011100001100000000 /
1)
#30000
0)
b1 '
b1 ,
b111011100110101100101000000000 (
b111011100110101100101000000000 -
b10001000110010100110110000000000 &
b10001000110010100110110000000000 +
#35000
1$
b1001101001011111010001000000000 "
b1001101001011111010001000000000 .
b1001101001011111010001000000000 /
1)
#40000
0)
b101 (
b101 -
b10100 &
b10100 +
#45000
0$
0#
b1111 "
b1111 .
b1111 /
1)
#50000
0)
b10 '
b10 ,
b111111110000000011111111 (
b111111110000000011111111 -
b11111111000000001111111100000000 &
b11111111000000001111111100000000 +
#55000
b0 "
b0 .
1)
#60000
0)
b11 '
b11 ,
#65000
1!
b11111111111111111111111111111111 "
b11111111111111111111111111111111 .
1)
#70000
0)
b100 '
b100 ,
#75000
1$
0!
1)
#80000
0)
b101 '
b101 ,
#85000
b0 "
b0 .
1)
#90000
0)
b110 '
b110 ,
b1 (
b1 -
b11111111111111111111111111111011 &
b11111111111111111111111111111011 +
#95000
0$
1!
b1 "
b1 .
1)
#100000
0)
b11111111111111111111111111111111 (
b11111111111111111111111111111111 -
b101 &
b101 +
#105000
0!
b0 "
b0 .
1)
#110000
0)
b111 '
b111 ,
b100 (
b100 -
b1 &
b1 +
#115000
1!
b10000 "
b10000 .
1)
#120000
0)
b1000 '
b1000 ,
b11 (
b11 -
b10000000 &
b10000000 +
#125000
0!
1)
